{
    "variants": {
        "east=false,north=false,south=false,up=false,west=false": { "model": "wall_mossy_post_3d" },
        "east=false,north=true,south=false,up=false,west=false":  { "model": "wall_mossy_a_n_3d" },
        "east=true,north=false,south=false,up=false,west=false":  { "model": "wall_mossy_a_n_3d", "y": 90, "uvlock": true },
        "east=false,north=false,south=true,up=false,west=false":  { "model": "wall_mossy_a_n_3d", "y": 180, "uvlock": true },
        "east=false,north=false,south=false,up=false,west=true":  { "model": "wall_mossy_a_n_3d", "y": 270, "uvlock": true },
        "east=true,north=true,south=false,up=false,west=false":   { "model": "wall_mossy_a_ne_3d" },
        "east=true,north=false,south=true,up=false,west=false":   { "model": "wall_mossy_a_ne_3d", "y": 90, "uvlock": true },
        "east=false,north=false,south=true,up=false,west=true":   { "model": "wall_mossy_a_ne_3d", "y": 180, "uvlock": true },
        "east=false,north=true,south=false,up=false,west=true":   { "model": "wall_mossy_a_ne_3d", "y": 270, "uvlock": true },
        "east=false,north=true,south=true,up=false,west=false":   { "model": "wall_mossy_a_ns_3d" },
        "east=true,north=false,south=false,up=false,west=true":   { "model": "wall_mossy_a_ns_3d", "y": 90, "uvlock": true },
        "east=true,north=true,south=true,up=false,west=false":    { "model": "wall_mossy_a_nse_3d" },
        "east=true,north=false,south=true,up=false,west=true":    { "model": "wall_mossy_a_nse_3d", "y": 90, "uvlock": true },
        "east=false,north=true,south=true,up=false,west=true":    { "model": "wall_mossy_a_nse_3d", "y": 180, "uvlock": true },
        "east=true,north=true,south=false,up=false,west=true":    { "model": "wall_mossy_a_nse_3d", "y": 270, "uvlock": true },
        "east=true,north=true,south=true,up=false,west=true":     { "model": "wall_mossy_a_nsew_3d" },
        "east=false,north=false,south=false,up=true,west=false":  { "model": "wall_mossy_post_3d" },
        "east=false,north=true,south=false,up=true,west=false":   { "model": "wall_mossy_n_3d" },
        "east=true,north=false,south=false,up=true,west=false":   { "model": "wall_mossy_n_3d", "y": 90, "uvlock": true },
        "east=false,north=false,south=true,up=true,west=false":   { "model": "wall_mossy_n_3d", "y": 180, "uvlock": true },
        "east=false,north=false,south=false,up=true,west=true":   { "model": "wall_mossy_n_3d", "y": 270, "uvlock": true },
        "east=true,north=true,south=false,up=true,west=false":    { "model": "wall_mossy_ne_3d" },
        "east=true,north=false,south=true,up=true,west=false":    { "model": "wall_mossy_ne_3d", "y": 90, "uvlock": true },
        "east=false,north=false,south=true,up=true,west=true":    { "model": "wall_mossy_ne_3d", "y": 180, "uvlock": true },
        "east=false,north=true,south=false,up=true,west=true":    { "model": "wall_mossy_ne_3d", "y": 270, "uvlock": true },
        "east=false,north=true,south=true,up=true,west=false":    { "model": "wall_mossy_ns_3d" },
        "east=true,north=false,south=false,up=true,west=true":    { "model": "wall_mossy_ns_3d", "y": 90, "uvlock": true },
        "east=true,north=true,south=true,up=true,west=false":     { "model": "wall_mossy_nse_3d" },
        "east=true,north=false,south=true,up=true,west=true":     { "model": "wall_mossy_nse_3d", "y": 90, "uvlock": true },
        "east=false,north=true,south=true,up=true,west=true":     { "model": "wall_mossy_nse_3d", "y": 180, "uvlock": true },
        "east=true,north=true,south=false,up=true,west=true":     { "model": "wall_mossy_nse_3d", "y": 270, "uvlock": true },
        "east=true,north=true,south=true,up=true,west=true":      { "model": "wall_mossy_nsew_3d" }
    }
}